{"provides":{"Carton::Tree":{"file":"lib/Carton/Tree.pm"},"Carton::Snapshot::Emitter":{"file":"lib/Carton/Snapshot/Emitter.pm"},"Carton::Builder":{"file":"lib/Carton/Builder.pm"},"Carton::Snapshot::Parser":{"file":"lib/Carton/Snapshot/Parser.pm"},"Carton":{"version":"1.000012","file":"lib/Carton.pm"},"Carton::Snapshot":{"file":"lib/Carton/Snapshot.pm"},"Carton::Environment":{"file":"lib/Carton/Environment.pm"},"Carton::CLI":{"file":"lib/Carton/CLI.pm"},"Carton::Mirror":{"file":"lib/Carton/Mirror.pm"},"Carton::Util":{"file":"lib/Carton/Util.pm"},"Carton::Index":{"file":"lib/Carton/Index.pm"},"Carton::Packer":{"file":"lib/Carton/Packer.pm"},"Carton::Dist::Core":{"file":"lib/Carton/Dist/Core.pm"},"Carton::CPANfile":{"file":"lib/Carton/CPANfile.pm"},"Carton::Dependency":{"file":"lib/Carton/Dependency.pm"},"Carton::Dist":{"file":"lib/Carton/Dist.pm"},"Carton::Package":{"file":"lib/Carton/Package.pm"},"Carton::Error":{"file":"lib/Carton/Error.pm"}},"pathname":"M/MI/MIYAGAWA/Carton-v1.0.12.tar.gz","target":"Carton","name":"Carton","version":"1.000012","dist":"Carton-v1.0.12"}